{
  "books": [
    {
      "title": "To Kill a Mockingbird",
      "author": "Harper Lee",
      "year_published": 1960,
      "isbn": "9780060935467"
    },
    {
      "title": "1984",
      "author": "George Orwell",
      "year_published": 1949,
      "isbn": "9780451524935"
    },
    {
      "title": "Pride and Prejudice",
      "author": "Jane Austen",
      "year_published": 1813,
      "isbn": "9780141439518"
    },
    {
      "title": "The Great Gatsby",
      "author": "F. Scott Fitzgerald",
      "year_published": 1925,
      "isbn": "9780743273565"
    },
    {
      "title": "The Catcher in the Rye",
      "author": "J.D. Salinger",
      "year_published": 1951,
      "isbn": "9780316769488"
    },
    {
      "title": "Moby-Dick",
      "author": "Herman Melville",
      "year_published": 1851,
      "isbn": "9780142437247"
    },
    {
      "title": "War and Peace",
      "author": "Leo Tolstoy",
      "year_published": 1869,
      "isbn": "9781400079988"
    },
    {
      "title": "The Odyssey",
      "author": "Homer",
      "year_published": -800,
      "isbn": "9780140268867"
    },
    {
      "title": "The Brothers Karamazov",
      "author": "Fyodor Dostoevsky",
      "year_published": 1880,
      "isbn": "9780374528379"
    },
    {
      "title": "Crime and Punishment",
      "author": "Fyodor Dostoevsky",
      "year_published": 1866,
      "isbn": "9780140449136"
    },
    {
      "title": "The Divine Comedy",
      "author": "Dante Alighieri",
      "year_published": 1320,
      "isbn": "9780142437223"
    },
    {
      "title": "Brave New World",
      "author": "Aldous Huxley",
      "year_published": 1932,
      "isbn": "9780060850524"
    },
    {
      "title": "Jane Eyre",
      "author": "Charlotte Brontë",
      "year_published": 1847,
      "isbn": "9780141441146"
    },
    {
      "title": "Wuthering Heights",
      "author": "Emily Brontë",
      "year_published": 1847,
      "isbn": "9780141439556"
    },
    {
      "title": "The Hobbit",
      "author": "J.R.R. Tolkien",
      "year_published": 1937,
      "isbn": "9780345339683"
    },
    {
      "title": "Fahrenheit 451",
      "author": "Ray Bradbury",
      "year_published": 1953,
      "isbn": "9781451673319"
    },
    {
      "title": "Anna Karenina",
      "author": "Leo Tolstoy",
      "year_published": 1877,
      "isbn": "9780143035008"
    },
    {
      "title": "Frankenstein",
      "author": "Mary Shelley",
      "year_published": 1818,
      "isbn": "9780141439471"
    },
    {
      "title": "The Grapes of Wrath",
      "author": "John Steinbeck",
      "year_published": 1939,
      "isbn": "9780143039433"
    },
    {
      "title": "The Lord of the Rings",
      "author": "J.R.R. Tolkien",
      "year_published": 1954,
      "isbn": "9780618640157"
    }
  ]
}
